setup.py
py3spider/__init__.py
py3spider.egg-info/PKG-INFO
py3spider.egg-info/SOURCES.txt
py3spider.egg-info/dependency_links.txt
py3spider.egg-info/not-zip-safe
py3spider.egg-info/requires.txt
py3spider.egg-info/top_level.txt