Metadata-Version: 1.0
Name: py3spider
Version: 1.0.7
Summary: 仿Scrapy实现，基于py3.4+的多线程异步网络爬虫，实例请访问https://github.com/ChenL1994/py3spider/tree/master/examples
Home-page: UNKNOWN
Author: 陈粮
Author-email: 1570184051@qq.com
License: MIT
Keywords: crawl,spider,asyncio,aiohttp,定向爬虫,异步爬虫
Platform: any
